README.rst
setup.py
PyAvroPhonetic.egg-info/PKG-INFO
PyAvroPhonetic.egg-info/SOURCES.txt
PyAvroPhonetic.egg-info/dependency_links.txt
PyAvroPhonetic.egg-info/requires.txt
PyAvroPhonetic.egg-info/top_level.txt
pyavrophonetic/__init__.py
pyavrophonetic/avro.py
pyavrophonetic/config.py
pyavrophonetic/resources/avrodict.json
pyavrophonetic/utils/__init__.py
pyavrophonetic/utils/count.py
pyavrophonetic/utils/validate.py