Metadata-Version: 1.1
Name: PyAvroPhonetic
Version: 0.1.3-p01
Summary: Python implementation of Avro Phonetic
Home-page: https://github.com/kaustavdm/pyAvroPhonetic
Author: Kaustav Das Modak
Author-email: kaustav.dasmodak@yahoo.co.in
License: GNU GPL v3 or later
Download-URL: https://github.com/kaustavdm/pyAvroPhonetic/zipball/0.1.3-p01
Platform: UNKNOWN
Classifier: Development Status :: 2 - Pre-Alpha
Classifier: Intended Audience :: Developers
Classifier: License :: OSI Approved :: GNU General Public License v3 or later (GPLv3+)
Classifier: Operating System :: OS Independent
Classifier: Programming Language :: Python :: 2.5
Classifier: Programming Language :: Python :: 2.6
Classifier: Programming Language :: Python :: 2.7
